pyinterleave/__about__.py
pyinterleave/__init__.py
pyinterleave/core/__init__.py
pyinterleave/methods/__init__.py
pyinterleave-0.0.1.dist-info/METADATA
pyinterleave-0.0.1.dist-info/WHEEL
pyinterleave-0.0.1.dist-info/licenses/AUTHORS.rst
pyinterleave-0.0.1.dist-info/licenses/LICENSE.txt
pyinterleave-0.0.1.dist-info/RECORD
