Metadata-Version: 2.1
Name: pyinterleave
Version: 0.0.1
Summary: Interleaving algorithms for faster experiments.
Project-URL: Documentation, https://github.com/maxent-ai/pyinterleave#readme
Project-URL: Issues, https://github.com/maxent-ai/pyinterleave/issues
Project-URL: Source, https://github.com/maxent-ai/pyinterleave
Author-email: maxentlabs <info@maxentlabs.com>
Classifier: Development Status :: 4 - Beta
Classifier: Programming Language :: Python
Classifier: Programming Language :: Python :: 3.7
Classifier: Programming Language :: Python :: 3.8
Classifier: Programming Language :: Python :: 3.9
Classifier: Programming Language :: Python :: 3.10
Classifier: Programming Language :: Python :: 3.11
Requires-Python: >=3.7
